{
    "version": "2019.2.2-192.6603.28",
    "description": "IntelliJ IDEA Community. Cross-Platform Java IDE for professional developers by JetBrains.",
    "homepage": "https://www.jetbrains.com/idea/",
    "url": "https://download.jetbrains.com/idea/ideaIC-2019.2.2.win.zip",
    "hash": "f63d1ef604cc2d6dbcd335b4e523ed29b8e2db0a464789de58ff0ce1fa9dab6b",
    "extract_to": "IDE",
    "installer": {
        "script": [
            "$currentDir = \"$(Split-Path \"$dir\")\\current\" -replace '\\\\', '/'",
            "$newDir = \"$(Split-Path \"$dir\")\\current\\IDE\" -replace '\\\\', '/'",
            "$IDE = \"$dir\\IDE\"",
            "$file = 'IDE\\bin\\idea.properties'",
            "if (-not (Test-Path \"$persist_dir\\$file\")) {",
            "    Write-Host 'File' \"$file\" 'does not exists. Creating.' -f Yellow",
            "    $file = \"$dir\\$file\"",
            "    $profileDir = \"$currentDir/profile\"",
            "    $CONT = Get-Content \"$file\"",
            "        # Replacing config options",
            "    $CONT = $CONT -replace '^# idea.config.path=.*$', \"idea.config.path=$profileDir/config\"",
            "    $CONT = $CONT -replace '^# idea.system.path=.*$', \"idea.system.path=$profileDir/system\"",
            "    $CONT = $CONT -replace '^# idea.plugins.path=', 'idea.plugins.path='",
            "    $CONT = $CONT -replace '^# idea.log.path=', 'idea.log.path='",
            "        # Rewrite properties file",
            "    Set-Content \"$file\" ($CONT -join \"`r`n\") -Force -Encoding Ascii",
            "}",
            "Remove-Item \"$IDE\\`$*\" -Force -Recurse"
        ]
    },
    "persist": [
        "IDE\\bin\\idea.properties",
        "profile"
    ],
    "architecture": {
        "64bit": {
            "bin": [
                "IDE\\bin\\idea.bat",
                "IDE\\bin\\idea64.exe"
            ],
            "shortcuts": [
                [
                    "IDE\\bin\\idea64.exe",
                    "IntelliJ IDEA Community"
                ]
            ]
        },
        "32bit": {
            "bin": "IDE\\bin\\idea.exe",
            "shortcuts": [
                [
                    "IDE\\bin\\idea.exe",
                    "IntelliJ IDEA Community"
                ]
            ]
        }
    },
    "checkver": {
        "url": "https://data.services.jetbrains.com/products/releases?code=IIC&latest=true&platform=zip&type=release",
        "regex": "version\":\"(?<ver>[\\d\\.]+)\".*\"build\":\"(?<build>[\\d\\.]+)\"",
        "replace": "${ver}-${build}"
    },
    "autoupdate": {
        "url": "https://download.jetbrains.com/idea/ideaIC-$matchHead.win.zip",
        "hash": {
            "url": "$url.sha256"
        }
    }
}
