{
    "version": "2019.3-193.5096.12",
    "description": "IntelliJ IDEA Community Early Access Program. Cross-Platform Java IDE for professional developers by JetBrains.",
    "homepage": "https://www.jetbrains.com/idea/",
    "url": "https://download.jetbrains.com/idea/ideaIC-193.5096.12.win.zip",
    "hash": "e5fc27dc535a3aa0918653902a2e7591e59e3519fcf1f90ce21b1a948220c17f",
    "extract_to": "IDE",
    "post_install": "Remove-Item \"$dir\\IDE\\`$*\" -Force -Recurse",
    "persist": "IDE\\bin\\idea.properties",
    "architecture": {
        "64bit": {
            "shortcuts": [
                [
                    "IDE\\bin\\idea64.exe",
                    "IntelliJ IDEA Community (Early Access Program)"
                ]
            ]
        },
        "32bit": {
            "shortcuts": [
                [
                    "IDE\\bin\\idea.exe",
                    "IntelliJ IDEA Community (Early Access Program)"
                ]
            ]
        }
    },
    "checkver": {
        "url": "https://data.services.jetbrains.com/products/releases?code=IIC&latest=true&platform=zip&type=eap",
        "regex": "version\":\"(?<ver>[\\d\\.]+)\".*\"build\":\"(?<build>[\\d\\.]+)\"",
        "replace": "${ver}-${build}"
    },
    "autoupdate": {
        "url": "https://download.jetbrains.com/idea/ideaIC-$preReleaseVersion.win.zip",
        "hash": {
            "url": "$url.sha256"
        }
    }
}
